chevron/__init__.py
chevron/main.py
chevron/metadata.py
chevron/renderer.py
chevron/tokenizer.py
chevron-0.13.1.dist-info/LICENSE
chevron-0.13.1.dist-info/METADATA
chevron-0.13.1.dist-info/WHEEL
chevron-0.13.1.dist-info/entry_points.txt
chevron-0.13.1.dist-info/top_level.txt
chevron-0.13.1.dist-info/RECORD
